LICENSE
MANIFEST.in
README.rst
setup.py
django_ga_simpletag.egg-info/PKG-INFO
django_ga_simpletag.egg-info/SOURCES.txt
django_ga_simpletag.egg-info/dependency_links.txt
django_ga_simpletag.egg-info/top_level.txt
docs/index.txt
gasimpletag/__init__.py
gasimpletag/admin.py
gasimpletag/apps.py
gasimpletag/models.py
gasimpletag/tests.py
gasimpletag/views.py
gasimpletag/migrations/__init__.py
gasimpletag/templates/example.html
gasimpletag/templatetags/google_analytics.py